pymunge/__init__.py
pymunge/_version.py
pymunge/context.py
pymunge/enums.py
pymunge/error.py
pymunge/raw.py
pymunge-0.1.3.dist-info/DESCRIPTION.rst
pymunge-0.1.3.dist-info/METADATA
pymunge-0.1.3.dist-info/RECORD
pymunge-0.1.3.dist-info/WHEEL
pymunge-0.1.3.dist-info/metadata.json
pymunge-0.1.3.dist-info/top_level.txt
